ffe/__init__.py
ffe/main.py
ffe/model.py
ffe/util.py
ffe-0.1.1.dist-info/entry_points.txt
ffe-0.1.1.dist-info/LICENSE
ffe-0.1.1.dist-info/WHEEL
ffe-0.1.1.dist-info/METADATA
ffe-0.1.1.dist-info/RECORD
