Metadata-Version: 2.1
Name: ffe
Version: 0.1.1
Summary: ffe: File/Folder Extensible manipulator (可扩展的文件操作工具)
Author-email: ahui <102419@gmail.com>
Requires-Python: >=3.10
Classifier: License :: OSI Approved :: MIT License
Requires-Dist: toml
Requires-Dist: tomli
Requires-Dist: click
Requires-Dist: appdirs
Requires-Dist: requests
Project-URL: Home, https://github.com/ahui2016/ffe
